lesscode_address/__init__.py
lesscode_address/version.py
lesscode_address/cpca/__init__.py
lesscode_address/cpca/drawer.py
lesscode_address/cpca/exceptions.py
lesscode_address/cpca/matcher.py
lesscode_address/cpca/structures.py
lesscode_address/cpca/resources/56_nations.csv
lesscode_address/cpca/resources/__init__.py
lesscode_address/cpca/resources/adcodes.csv
lesscode_address/dict/__init__.py
lesscode_address/dict/address.csv
lesscode_address/dict/areas.json
lesscode_address/dict/city_tree.json
lesscode_address/dict/county_tree.json
lesscode_address/dict/province_tree.json
lesscode_address/dict/retrieval_city.json
lesscode_address/dict/retrieval_county.json
lesscode_address/dict/retrieval_province.json
lesscode_address/dict/retrieval_town.json
lesscode_address/dict/town_tree.json
lesscode_address/src/__init__.py
lesscode_address/src/address_parser.py
lesscode_address/src/address_recognition.py
lesscode_address/src/recognition_strategy.py
lesscode_address-0.0.0.dist-info/METADATA
lesscode_address-0.0.0.dist-info/WHEEL
lesscode_address-0.0.0.dist-info/top_level.txt
lesscode_address-0.0.0.dist-info/RECORD
